pysphere/__init__.py
pysphere/version.py
pysphere/vi_event_history_collector.py
pysphere/vi_history_collector.py
pysphere/vi_managed_entity.py
pysphere/vi_mor.py
pysphere/vi_performance_manager.py
pysphere/vi_property.py
pysphere/vi_server.py
pysphere/vi_snapshot.py
pysphere/vi_task.py
pysphere/vi_task_history_collector.py
pysphere/vi_virtual_machine.py
pysphere/ZSI/LBNLCopyright
pysphere/ZSI/ServiceContainer.py
pysphere/ZSI/ServiceProxy.py
pysphere/ZSI/TC.py
pysphere/ZSI/TCapache.py
pysphere/ZSI/TCcompound.py
pysphere/ZSI/TCnumbers.py
pysphere/ZSI/TCtimes.py
pysphere/ZSI/__init__.py
pysphere/ZSI/address.py
pysphere/ZSI/auth.py
pysphere/ZSI/client.py
pysphere/ZSI/digest_auth.py
pysphere/ZSI/dispatch.py
pysphere/ZSI/fault.py
pysphere/ZSI/parse.py
pysphere/ZSI/resolvers.py
pysphere/ZSI/schema.py
pysphere/ZSI/typeinterpreter.py
pysphere/ZSI/version.py
pysphere/ZSI/writer.py
pysphere/ZSI/generate/__init__.py
pysphere/ZSI/generate/commands.py
pysphere/ZSI/generate/containers.py
pysphere/ZSI/generate/pyclass.py
pysphere/ZSI/generate/utility.py
pysphere/ZSI/generate/wsdl2dispatch.py
pysphere/ZSI/generate/wsdl2python.py
pysphere/ZSI/wstools/MIMEAttachment.py
pysphere/ZSI/wstools/Namespaces.py
pysphere/ZSI/wstools/TimeoutSocket.py
pysphere/ZSI/wstools/UserTuple.py
pysphere/ZSI/wstools/Utility.py
pysphere/ZSI/wstools/WSDLTools.py
pysphere/ZSI/wstools/XMLSchema.py
pysphere/ZSI/wstools/XMLname.py
pysphere/ZSI/wstools/__init__.py
pysphere/ZSI/wstools/c14n.py
pysphere/ZSI/wstools/logging.py
pysphere/resources/VimService_services.py
pysphere/resources/VimService_services_types.py
pysphere/resources/__init__.py
pysphere/resources/vi_exception.py
pysphere3-0.1.8.dist-info/METADATA
pysphere3-0.1.8.dist-info/WHEEL
pysphere3-0.1.8.dist-info/top_level.txt
pysphere3-0.1.8.dist-info/RECORD
